{
  "kind": "collectionType",
  "collectionName": "locations",
  "info": {
    "singularName": "location",
    "pluralName": "locations",
    "displayName": "Location",
    "description": ""
  },
  "options": {
    "draftAndPublish": true
  },
  "pluginOptions": {},
  "attributes": {
    "title": {
      "type": "string",
      "required": true
    },
    "projects": {
      "type": "relation",
      "relation": "oneToMany",
      "target": "api::project.project"
    },
    "main_location": {
      "type": "relation",
      "relation": "oneToOne",
      "target": "api::main-location.main-location"
    }
  }
}
